virustotal_tddschn/__init__.py
virustotal_tddschn/brew_utils.py
virustotal_tddschn/config.py
virustotal_tddschn/hashing.py
virustotal_tddschn/types.py
virustotal_tddschn/utils.py
virustotal_tddschn/virustotal_sum_search.py
virustotal_tddschn-0.2.3.dist-info/LICENSE
virustotal_tddschn-0.2.3.dist-info/METADATA
virustotal_tddschn-0.2.3.dist-info/WHEEL
virustotal_tddschn-0.2.3.dist-info/entry_points.txt
virustotal_tddschn-0.2.3.dist-info/RECORD
