Metadata-Version: 2.1
Name: virustotal-tddschn
Version: 0.2.3
Summary: VirusTotal Utility Scripts
Home-page: https://github.com/tddschn/virustotal-tddschn
License: MIT
Keywords: virustotal
Author: Xinyuan Chen
Author-email: 45612704+tddschn@users.noreply.github.com
Requires-Python: >=3.11,<4.0
Classifier: License :: OSI Approved :: MIT License
Classifier: Programming Language :: Python :: 3
Classifier: Programming Language :: Python :: 3.11
Classifier: Topic :: Utilities
Requires-Dist: vt-py (>=0.17.3,<0.18.0)
Project-URL: Bug Tracker, https://github.com/tddschn/virustotal-tddschn/issues
Project-URL: Repository, https://github.com/tddschn/virustotal-tddschn
